odoo9_addon_delivery_multi_destination-9.0.1.0.0-py2.7-nspkg.pth
odoo9_addon_delivery_multi_destination-9.0.1.0.0.dist-info/DESCRIPTION.rst
odoo9_addon_delivery_multi_destination-9.0.1.0.0.dist-info/METADATA
odoo9_addon_delivery_multi_destination-9.0.1.0.0.dist-info/RECORD
odoo9_addon_delivery_multi_destination-9.0.1.0.0.dist-info/WHEEL
odoo9_addon_delivery_multi_destination-9.0.1.0.0.dist-info/metadata.json
odoo9_addon_delivery_multi_destination-9.0.1.0.0.dist-info/namespace_packages.txt
odoo9_addon_delivery_multi_destination-9.0.1.0.0.dist-info/top_level.txt
odoo_addons/delivery_multi_destination/README.rst
odoo_addons/delivery_multi_destination/__init__.py
odoo_addons/delivery_multi_destination/__openerp__.py
odoo_addons/delivery_multi_destination/hooks.py
odoo_addons/delivery_multi_destination/demo/delivery_carrier_demo.xml
odoo_addons/delivery_multi_destination/models/__init__.py
odoo_addons/delivery_multi_destination/models/delivery_carrier.py
odoo_addons/delivery_multi_destination/static/description/icon.png
odoo_addons/delivery_multi_destination/tests/__init__.py
odoo_addons/delivery_multi_destination/tests/test_delivery_multi_destination.py
odoo_addons/delivery_multi_destination/views/delivery_carrier_view.xml
